hugging_quik/__init__.py
hugging_quik/io.py
hugging_quik/model.py
hugging_quik/token.py
hugging_quik/utils.py
hugging_quik/tests/__init__.py
hugging_quik/tests/conftest.py
hugging_quik/tests/test_hugging.py
hugging_quik-0.0.1.dist-info/METADATA
hugging_quik-0.0.1.dist-info/WHEEL
hugging_quik-0.0.1.dist-info/top_level.txt
hugging_quik-0.0.1.dist-info/RECORD
