Metadata-Version: 2.1
Name: hugging-quik
Version: 0.0.1
Summary: helper package to make loading/unloading huggingface models quik-er
Home-page: https://github.com/donchesworth/hugging-quik
Author: Don Chesworth
Author-email: donald.chesworth@gmail.com
License: BSD
Platform: UNKNOWN
Classifier: License :: OSI Approved :: BSD License
Classifier: Programming Language :: Python :: 3.8
Requires-Dist: torch (>=1.7.0)
Requires-Dist: pandas (>=1.1)
Requires-Dist: transformers (==4.16.2)
Requires-Dist: sentencepiece
Requires-Dist: pytest
Requires-Dist: pytest-cov
Requires-Dist: codecov
Requires-Dist: numpy (>=1.21.0)
Requires-Dist: bump2version
